bisstats/__init__.py
bisstats/http_request.py
bisstats-0.0.1.dist-info/LICENSE
bisstats-0.0.1.dist-info/METADATA
bisstats-0.0.1.dist-info/WHEEL
bisstats-0.0.1.dist-info/top_level.txt
bisstats-0.0.1.dist-info/RECORD
