Metadata-Version: 2.1
Name: bisstats
Version: 0.0.1
Author-email: Niall O'Connor <zechs.marquie@gmail.com>
Classifier: Programming Language :: Python :: 3
Classifier: License :: OSI Approved :: MIT License
Classifier: Operating System :: OS Independent
Requires-Python: >=3.7
License-File: LICENSE
Requires-Dist: requests
Requires-Dist: pyjson
